cdk_build_lambda_layer/__init__.py
cdk_build_lambda_layer/constructs.py
cdk_build_lambda_layer-0.1.0.dist-info/METADATA
cdk_build_lambda_layer-0.1.0.dist-info/WHEEL
cdk_build_lambda_layer-0.1.0.dist-info/RECORD
