Metadata-Version: 2.1
Name: cdk-build-lambda-layer
Version: 0.1.0
Summary: 
Author: Daniel Donovan
Author-email: spitfiredd@gmail.com
Requires-Python: >=3.11,<4.0
Classifier: Programming Language :: Python :: 3
Classifier: Programming Language :: Python :: 3.11
Requires-Dist: aws-cdk-lib (>=2.101.1,<3.0.0)
Requires-Dist: boto3 (>=1.28.65,<2.0.0)
Requires-Dist: importlib-metadata (>=6.8.0,<7.0.0)
